pure3270/__init__.py
pure3270/session.py
pure3270/emulation/__init__.py
pure3270/emulation/ebcdic.py
pure3270/emulation/screen_buffer.py
pure3270/patching/__init__.py
pure3270/patching/patching.py
pure3270/patching/s3270_wrapper.py
pure3270/protocol/__init__.py
pure3270/protocol/data_stream.py
pure3270/protocol/exceptions.py
pure3270/protocol/negotiator.py
pure3270/protocol/printer.py
pure3270/protocol/ssl_wrapper.py
pure3270/protocol/tn3270_handler.py
pure3270/protocol/tn3270e_header.py
pure3270/protocol/utils.py
tests/__init__.py
tests/conftest.py
tests/test_aid_support.py
tests/test_cli.py
tests/test_data_stream.py
tests/test_emulation.py
tests/test_emulation_ebcdic.py
tests/test_extended_field_attributes.py
tests/test_field_modification.py
tests/test_integration.py
tests/test_missing_s3270_actions.py
tests/test_negotiator_enhancements.py
tests/test_negotiator_missing_coverage.py
tests/test_patching.py
tests/test_patching_advanced.py
tests/test_patching_integration.py
tests/test_patching_s3270_wrapper.py
tests/test_printer.py
tests/test_protocol.py
tests/test_protocol_errors.py
tests/test_protocol_performance.py
tests/test_protocol_utils.py
tests/test_session.py
tests/test_ssl_wrapper.py
tests/test_structured_fields.py
tests/test_tn3270_handler.py
tests/test_tn3270e_header.py
pure3270-0.3.1.dist-info/METADATA
pure3270-0.3.1.dist-info/WHEEL
pure3270-0.3.1.dist-info/top_level.txt
pure3270-0.3.1.dist-info/RECORD
