Metadata-Version: 2.4
Name: pure3270
Version: 0.3.1
Summary: Pure Python 3270 emulator
Author: Pure3270 Developers
Classifier: Programming Language :: Python :: 3
Classifier: Programming Language :: Python :: 3.8
Classifier: Programming Language :: Python :: 3.9
Classifier: Programming Language :: Python :: 3.10
Classifier: Programming Language :: Python :: 3.11
Classifier: Programming Language :: Python :: 3.12
Classifier: License :: OSI Approved :: MIT License
Classifier: Operating System :: OS Independent
Requires-Python: >=3.8
Provides-Extra: test
Requires-Dist: pytest>=7.0; extra == "test"
Requires-Dist: pytest-asyncio>=0.21; extra == "test"
Requires-Dist: pytest-benchmark>=4.0; extra == "test"
Requires-Dist: flake8>=7.0; extra == "test"
Requires-Dist: black>=24.0; extra == "test"
Requires-Dist: pytest-cov>=5.0; extra == "test"
Requires-Dist: p3270>=0.1.6; extra == "test"
Dynamic: requires-python
